wikiMD/__init__.py
wikiMD/__main__.py
wikiMD/script.py
wikiMD/wiki.j2
wikiMD/wikiMD.py
wikimd-0.6.0.dist-info/entry_points.txt
wikimd-0.6.0.dist-info/LICENSE
wikimd-0.6.0.dist-info/WHEEL
wikimd-0.6.0.dist-info/METADATA
wikimd-0.6.0.dist-info/RECORD
