Metadata-Version: 2.1
Name: wikimd
Version: 0.6.0
Summary: Turn Wikipedia in markmap friendly markdown
Author: John Capobianco
Author-email: ptcapo@gmail.com
Requires-Python: >=3.9,<4.0
Classifier: Programming Language :: Python :: 3
Classifier: Programming Language :: Python :: 3.10
Classifier: Programming Language :: Python :: 3.9
Requires-Dist: Jinja2 (>=3.0.3,<4.0.0)
Requires-Dist: wikipedia (>=1.4.0,<2.0.0)
